hearthis
