Metadata-Version: 2.1
Name: python-hearthis
Version: 1.0.1
Summary: Unofficial Python library for hearthis.io API https://hearthis.at/api-v2/
Home-page: https://github.com/jinchuuriki91/python-hearthis
Author: Gandhar Pednekar
Author-email: gandhar.pednekar15@gmail.com
License: MIT
Keywords: python library requests hearthis API
Platform: OS Independent
Classifier: Development Status :: 4 - Beta
Classifier: Intended Audience :: Developers
Classifier: Topic :: Software Development :: Libraries :: Python Modules
Classifier: License :: OSI Approved :: MIT License
Classifier: Operating System :: OS Independent
Classifier: Programming Language :: Python :: 3.6
